<DOMSymbolItem xmlns:xsi="http://www.w3.org/2001/XMLSchema-instance" xmlns="http://ns.adobe.com/xfl/2008/" symbolType="graphic" linkageExportInFirstFrame="false" name="Shapes/Shape 11">
  <timeline>
    <DOMTimeline name="Shape 11">
      <layers>
        <DOMLayer name="Shape Sublayer 1" color="#4f80ff">
          <frames>
            <DOMFrame index="0">
              <elements>
                <DOMShape>
                  <fills>
                    <FillStyle index="1">
                      <SolidColor color="#000000" />
                    </FillStyle>
                  </fills>
                  <edges>
                    <Edge fillStyle0="1" edges="!19 -1633[-99 -1630 -120 -1562" />
                    <Edge fillStyle0="1" edges="!-120 -1562[-141 -1494 -143 -1430" />
                    <Edge fillStyle0="1" edges="!-143 -1430|-150 -1333" />
                    <Edge fillStyle0="1" edges="!-150 -1333|-149 -1333" />
                    <Edge fillStyle0="1" edges="!-149 -1333|-150 -1329" />
                    <Edge fillStyle0="1" edges="!-150 -1329|-155 -1315" />
                    <Edge fillStyle0="1" edges="!-155 -1315[-179 -1312 -239 -1236" />
                    <Edge fillStyle0="1" edges="!-239 -1236|-244 -1230" />
                    <Edge fillStyle0="1" edges="!-244 -1230|-260 -1209" />
                    <Edge fillStyle0="1" edges="!-260 -1209|-270 -1194" />
                    <Edge fillStyle0="1" edges="!-270 -1194[-515 -1019 -538 -502" />
                    <Edge fillStyle0="1" edges="!-538 -502|-730 -562" />
                    <Edge fillStyle0="1" edges="!-730 -562|-727 -542" />
                    <Edge fillStyle0="1" edges="!-727 -542|-757 -550" />
                    <Edge fillStyle0="1" edges="!-757 -550[-756 -628 -808 -664" />
                    <Edge fillStyle0="1" edges="!-808 -664[-859 -700 -887 -700" />
                    <Edge fillStyle0="1" edges="!-887 -700[-915 -700 -934 -655" />
                    <Edge fillStyle0="1" edges="!-934 -655[-938 -665 -971 -677" />
                    <Edge fillStyle0="1" edges="!-971 -677|-1012 -688" />
                    <Edge fillStyle0="1" edges="!-1012 -688[-1042 -688 -1066 -665" />
                    <Edge fillStyle0="1" edges="!-1066 -665[-1089 -642 -1089 -613" />
                    <Edge fillStyle0="1" edges="!-1089 -613|-1084 -597" />
                    <Edge fillStyle0="1" edges="!-1084 -597|-1101 -585" />
                    <Edge fillStyle0="1" edges="!-1101 -585[-1119 -566 -1119 -538" />
                    <Edge fillStyle0="1" edges="!-1119 -538|-1118 -509" />
                    <Edge fillStyle0="1" edges="!-1118 -509|-1108 -494" />
                    <Edge fillStyle0="1" edges="!-1108 -494|-1114 -488" />
                    <Edge fillStyle0="1" edges="!-1114 -488[-1129 -469 -1129 -425" />
                    <Edge fillStyle0="1" edges="!-1129 -425[-1129 -363 -1042 -322" />
                    <Edge fillStyle0="1" edges="!-1042 -322[-956 -282 -846 -303" />
                    <Edge fillStyle0="1" edges="!-846 -303|-819 -292" />
                    <Edge fillStyle0="1" edges="!-819 -292|-828 -282" />
                    <Edge fillStyle0="1" edges="!-828 -282[-667 -216 -496 -195" />
                    <Edge fillStyle0="1" edges="!-496 -195[-507 -33 -508 112" />
                    <Edge fillStyle0="1" edges="!-508 112|-508 125" />
                    <Edge fillStyle0="1" edges="!-508 125|-507 185" />
                    <Edge fillStyle0="1" edges="!-507 185|-506 209" />
                    <Edge fillStyle0="1" edges="!-506 209|-506 260" />
                    <Edge fillStyle0="1" edges="!-506 260|-506 265" />
                    <Edge fillStyle0="1" edges="!-506 265|-505 331" />
                    <Edge fillStyle0="1" edges="!-505 331|-505 332" />
                    <Edge fillStyle0="1" edges="!-505 332|-484 335" />
                    <Edge fillStyle0="1" edges="!-484 335|-349 352" />
                    <Edge fillStyle0="1" edges="!-349 352|-353 277" />
                    <Edge fillStyle0="1" edges="!-353 277|-353 242" />
                    <Edge fillStyle0="1" edges="!-353 242|-351 29" />
                    <Edge fillStyle0="1" edges="!-351 29|-351 -21" />
                    <Edge fillStyle0="1" edges="!-351 -21|-303 -8" />
                    <Edge fillStyle0="1" edges="!-303 -8|-284 -6" />
                    <Edge fillStyle0="1" edges="!-284 -6|-255 -5" />
                    <Edge fillStyle0="1" edges="!-255 -5|-234 39" />
                    <Edge fillStyle0="1" edges="!-234 39|-187 -8" />
                    <Edge fillStyle0="1" edges="!-187 -8[-177 24 -139 37" />
                    <Edge fillStyle0="1" edges="!-139 37|-137 37" />
                    <Edge fillStyle0="1" edges="!-137 37|-137 40" />
                    <Edge fillStyle0="1" edges="!-137 40[-122 79 -97 97" />
                    <Edge fillStyle0="1" edges="!-97 97[-78 111 -46 116" />
                    <Edge fillStyle0="1" edges="!-46 116|-44 199" />
                    <Edge fillStyle0="1" edges="!-44 199|-38 365" />
                    <Edge fillStyle0="1" edges="!-38 365[282 437 561 327" />
                    <Edge fillStyle0="1" edges="!561 327[574 100 571 -112" />
                    <Edge fillStyle0="1" edges="!571 -112|644 -149" />
                    <Edge fillStyle0="1" edges="!644 -149[708 -184 771 -254" />
                    <Edge fillStyle0="1" edges="!771 -254[822 -310 742 -555" />
                    <Edge fillStyle0="1" edges="!742 -555[580 -1142 243 -1243" />
                    <Edge fillStyle0="1" edges="!243 -1243|229 -1277" />
                    <Edge fillStyle0="1" edges="!229 -1277|214 -1305" />
                    <Edge fillStyle0="1" edges="!214 -1305|206 -1321" />
                    <Edge fillStyle0="1" edges="!206 -1321|189 -1348" />
                    <Edge fillStyle0="1" edges="!189 -1348|176 -1365" />
                    <Edge fillStyle0="1" edges="!176 -1365|171 -1370" />
                    <Edge fillStyle0="1" edges="!171 -1370|169 -1373" />
                    <Edge fillStyle0="1" edges="!169 -1373|155 -1386" />
                    <Edge fillStyle0="1" edges="!155 -1386|155 -1445" />
                    <Edge fillStyle0="1" edges="!155 -1445|149 -1523" />
                    <Edge fillStyle0="1" edges="!149 -1523[137 -1636 19 -1633" />
                    <Edge fillStyle1="1" edges="!-150 -1327|-154 -1310" />
                    <Edge fillStyle1="1" edges="!-154 -1310|-152 -1312" />
                    <Edge fillStyle1="1" edges="!-152 -1312|-150 -1314" />
                    <Edge fillStyle1="1" edges="!-150 -1314|-150 -1306" />
                    <Edge fillStyle1="1" edges="!-150 -1306|-150 -1309" />
                    <Edge fillStyle1="1" edges="!-150 -1309|-150 -1312" />
                    <Edge fillStyle1="1" edges="!-150 -1312|-150 -1313" />
                    <Edge fillStyle1="1" edges="!-150 -1313|-150 -1315" />
                    <Edge fillStyle1="1" edges="!-150 -1315|-150 -1327" />
                  </edges>
                </DOMShape>
              </elements>
            </DOMFrame>
          </frames>
        </DOMLayer>
      </layers>
    </DOMTimeline>
  </timeline>
</DOMSymbolItem>
