<DOMSymbolItem xmlns:xsi="http://www.w3.org/2001/XMLSchema-instance" xmlns="http://ns.adobe.com/xfl/2008/" symbolType="graphic" linkageExportInFirstFrame="false" name="Shapes/Shape 12">
  <timeline>
    <DOMTimeline name="Shape 12">
      <layers>
        <DOMLayer name="Shape Sublayer 1" color="#4f80ff">
          <frames>
            <DOMFrame index="0">
              <elements>
                <DOMShape>
                  <fills>
                    <FillStyle index="1">
                      <SolidColor color="#e6e6e6" />
                    </FillStyle>
                    <FillStyle index="2">
                      <SolidColor color="#e5e5e5" />
                    </FillStyle>
                    <FillStyle index="3">
                      <SolidColor color="#e5e5e5" />
                    </FillStyle>
                    <FillStyle index="4">
                      <SolidColor color="#5c5c5c" />
                    </FillStyle>
                  </fills>
                  <strokes>
                    <StrokeStyle index="1">
                      <SolidStroke weight="1" scaleMode="normal">
                        <fill>
                          <SolidColor color="#000000" />
                        </fill>
                      </SolidStroke>
                    </StrokeStyle>
                  </strokes>
                  <edges>
                    <Edge strokeStyle="1" fillStyle0="1" edges="!161 -1437|161 -1497" />
                    <Edge strokeStyle="1" fillStyle0="1" edges="!161 -1497|155 -1577" />
                    <Edge strokeStyle="1" fillStyle0="1" edges="!155 -1577[142 -1693 26 -1690" />
                    <Edge strokeStyle="1" fillStyle0="1" edges="!26 -1690[-91 -1687 -112 -1617" />
                    <Edge strokeStyle="1" fillStyle0="1" edges="!-112 -1617[-133 -1548 -135 -1482" />
                    <Edge strokeStyle="1" fillStyle0="1" edges="!-135 -1482|-142 -1383" />
                    <Edge strokeStyle="1" fillStyle0="1" edges="!-142 -1383|-141 -1383" />
                    <Edge strokeStyle="1" fillStyle0="1" edges="!-141 -1383|-142 -1379" />
                    <Edge strokeStyle="1" fillStyle0="1" fillStyle1="4" edges="!-142 -1379|-142 -1377" />
                    <Edge strokeStyle="1" fillStyle0="1" edges="!-142 -1377|-142 -1364" />
                    <Edge strokeStyle="1" fillStyle0="1" edges="!-142 -1364|-142 -1363" />
                    <Edge strokeStyle="1" fillStyle0="1" fillStyle1="3" edges="!-142 -1363|-142 -1345" />
                    <Edge strokeStyle="1" fillStyle0="1" fillStyle1="3" edges="!-142 -1345[-142 -1280 -109 -1227" />
                    <Edge strokeStyle="1" fillStyle0="1" fillStyle1="2" edges="!-109 -1227|-54 -1224" />
                    <Edge strokeStyle="1" fillStyle0="1" fillStyle1="3" edges="!-54 -1224[156 -1301 163 -1410" />
                    <Edge strokeStyle="1" fillStyle0="1" fillStyle1="1" edges="!163 -1410|161 -1416" />
                    <Edge strokeStyle="1" fillStyle0="1" fillStyle1="1" edges="!161 -1416|161 -1437" />
                    <Edge strokeStyle="1" fillStyle1="4" edges="!161 -1437|175 -1424" />
                    <Edge strokeStyle="1" fillStyle1="4" edges="!175 -1424|177 -1421" />
                    <Edge strokeStyle="1" fillStyle1="4" edges="!177 -1421|181 -1416" />
                    <Edge strokeStyle="1" fillStyle1="4" edges="!181 -1416|194 -1398" />
                    <Edge strokeStyle="1" fillStyle1="4" edges="!194 -1398|212 -1371" />
                    <Edge strokeStyle="1" fillStyle1="4" edges="!212 -1371|219 -1354" />
                    <Edge strokeStyle="1" fillStyle1="4" edges="!219 -1354|234 -1326" />
                    <Edge strokeStyle="1" fillStyle1="4" edges="!234 -1326|248 -1291" />
                    <Edge strokeStyle="1" fillStyle1="4" edges="!248 -1291|279 -1269" />
                    <Edge strokeStyle="1" fillStyle1="4" edges="!279 -1269|319 -1239" />
                    <Edge strokeStyle="1" fillStyle1="4" edges="!319 -1239[443 -1144 499 -1064" />
                    <Edge strokeStyle="1" fillStyle1="4" edges="!499 -1064|501 -1061" />
                    <Edge strokeStyle="1" fillStyle1="4" edges="!501 -1061|506 -1055" />
                    <Edge strokeStyle="1" fillStyle1="4" edges="!506 -1055[575 -966 610 -769" />
                    <Edge strokeStyle="1" fillStyle1="4" edges="!610 -769|626 -667" />
                    <Edge strokeStyle="1" fillStyle1="4" edges="!626 -667|628 -657" />
                    <Edge strokeStyle="1" fillStyle1="4" edges="!628 -657|633 -606" />
                    <Edge strokeStyle="1" fillStyle1="4" edges="!633 -606|638 -553" />
                    <Edge strokeStyle="1" fillStyle1="4" edges="!638 -553|624 49" />
                    <Edge strokeStyle="1" fillStyle1="4" edges="!624 49|624 59" />
                    <Edge strokeStyle="1" fillStyle1="4" edges="!624 59|623 172" />
                    <Edge strokeStyle="1" edges="!623 172|621 201" />
                    <Edge strokeStyle="1" fillStyle1="4" edges="!621 201|621 207" />
                    <Edge strokeStyle="1" fillStyle1="4" edges="!621 207|610 209" />
                    <Edge strokeStyle="1" fillStyle1="4" edges="!610 209|599 211" />
                    <Edge strokeStyle="1" fillStyle1="4" edges="!599 211|595 212" />
                    <Edge strokeStyle="1" fillStyle1="3" edges="!595 212|591 244" />
                    <Edge strokeStyle="1" fillStyle1="3" edges="!591 244|585 278" />
                    <Edge strokeStyle="1" fillStyle1="3" edges="!585 278|584 278" />
                    <Edge strokeStyle="1" fillStyle1="3" edges="!584 278|581 279" />
                    <Edge strokeStyle="1" fillStyle1="3" edges="!581 279|573 280" />
                    <Edge strokeStyle="1" fillStyle1="3" edges="!573 280|572 280" />
                    <Edge strokeStyle="1" fillStyle1="1" edges="!572 280|578 328" />
                    <Edge strokeStyle="1" fillStyle1="1" edges="!578 328[582 370 559 418" />
                    <Edge strokeStyle="1" fillStyle1="1" edges="!559 418[541 452 523 470" />
                    <Edge strokeStyle="1" fillStyle1="1" edges="!523 470[543 522 598 522" />
                    <Edge strokeStyle="1" fillStyle1="1" edges="!598 522|610 523" />
                    <Edge strokeStyle="1" fillStyle1="1" edges="!610 523|637 528" />
                    <Edge strokeStyle="1" fillStyle1="1" edges="!637 528[651 537 649 574" />
                    <Edge strokeStyle="1" fillStyle1="1" edges="!649 574|638 598" />
                    <Edge strokeStyle="1" fillStyle1="1" edges="!638 598|610 622" />
                    <Edge strokeStyle="1" fillStyle1="1" edges="!610 622|607 623" />
                    <Edge strokeStyle="1" fillStyle1="1" edges="!607 623|517 629" />
                    <Edge strokeStyle="1" fillStyle1="1" edges="!517 629|501 637" />
                    <Edge strokeStyle="1" fillStyle1="1" edges="!501 637|498 638" />
                    <Edge strokeStyle="1" fillStyle1="1" edges="!498 638|451 649" />
                    <Edge strokeStyle="1" fillStyle1="1" edges="!451 649[396 649 366 618" />
                    <Edge strokeStyle="1" fillStyle1="1" edges="!366 618|358 609" />
                    <Edge strokeStyle="1" fillStyle1="1" edges="!358 609[287 582 270 523" />
                    <Edge strokeStyle="1" fillStyle1="1" edges="!270 523[254 462 256 369" />
                    <Edge strokeStyle="1" fillStyle1="1" edges="!256 369|258 355" />
                    <Edge strokeStyle="1" fillStyle1="4" edges="!258 355|219 359" />
                    <Edge strokeStyle="1" fillStyle1="4" edges="!219 359|160 363" />
                    <Edge strokeStyle="1" fillStyle1="4" edges="!160 363|-31 350" />
                    <Edge strokeStyle="1" fillStyle1="4" edges="!-31 350|-37 181" />
                    <Edge strokeStyle="1" fillStyle1="4" edges="!-37 181|-41 20" />
                    <Edge strokeStyle="1" fillStyle1="4" edges="!-41 20|-41 0" />
                    <Edge strokeStyle="1" fillStyle1="3" edges="!-41 0|-121 -8" />
                    <Edge strokeStyle="1" fillStyle1="3" edges="!-121 -8|-190 -19" />
                    <Edge strokeStyle="1" fillStyle1="2" edges="!-190 -19|-225 17" />
                    <Edge strokeStyle="1" fillStyle1="2" edges="!-225 17|-243 -23" />
                    <Edge strokeStyle="1" fillStyle1="3" edges="!-243 -23[-287 -13 -342 -23" />
                    <Edge strokeStyle="1" fillStyle1="4" edges="!-342 -23|-342 7" />
                    <Edge strokeStyle="1" fillStyle1="4" edges="!-342 7|-344 224" />
                    <Edge strokeStyle="1" fillStyle1="4" edges="!-344 224|-344 260" />
                    <Edge strokeStyle="1" fillStyle1="4" edges="!-344 260|-340 336" />
                    <Edge strokeStyle="1" fillStyle1="4" edges="!-340 336|-494 316" />
                    <Edge strokeStyle="1" fillStyle1="1" edges="!-494 316|-486 318" />
                    <Edge strokeStyle="1" fillStyle1="1" edges="!-486 318|-473 320" />
                    <Edge strokeStyle="1" fillStyle1="1" edges="!-473 320|-476 325" />
                    <Edge strokeStyle="1" fillStyle1="1" edges="!-476 325[-497 357 -510 362" />
                    <Edge strokeStyle="1" fillStyle1="1" edges="!-510 362[-491 375 -480 397" />
                    <Edge strokeStyle="1" fillStyle1="1" edges="!-480 397|-457 450" />
                    <Edge strokeStyle="1" fillStyle1="1" edges="!-457 450[-445 481 -479 529" />
                    <Edge strokeStyle="1" fillStyle1="1" edges="!-479 529|-485 561" />
                    <Edge strokeStyle="1" fillStyle1="1" edges="!-485 561[-491 576 -531 574" />
                    <Edge strokeStyle="1" fillStyle1="1" edges="!-531 574[-571 571 -619 503" />
                    <Edge strokeStyle="1" fillStyle1="1" edges="!-619 503[-648 460 -661 407" />
                    <Edge strokeStyle="1" fillStyle1="1" edges="!-661 407[-668 371 -668 331" />
                    <Edge strokeStyle="1" fillStyle1="1" edges="!-668 331|-667 284" />
                    <Edge strokeStyle="1" fillStyle1="1" edges="!-667 284|-666 279" />
                    <Edge strokeStyle="1" fillStyle1="1" edges="!-666 279|-666 276" />
                    <Edge strokeStyle="1" fillStyle1="1" edges="!-666 276|-657 236" />
                    <Edge strokeStyle="1" fillStyle1="3" edges="!-657 236|-662 236" />
                    <Edge strokeStyle="1" fillStyle1="3" edges="!-662 236|-661 222" />
                    <Edge strokeStyle="1" fillStyle1="3" edges="!-661 222|-658 177" />
                    <Edge strokeStyle="1" fillStyle1="4" edges="!-658 177|-675 175" />
                    <Edge strokeStyle="1" fillStyle1="4" edges="!-675 175|-681 174" />
                    <Edge strokeStyle="1" fillStyle1="4" edges="!-681 174|-647 -351" />
                    <Edge strokeStyle="1" fillStyle1="4" edges="!-647 -351[-627 -628 -577 -821" />
                    <Edge strokeStyle="1" fillStyle1="4" edges="!-577 -821[-527 -1013 -444 -1103" />
                    <Edge strokeStyle="1" fillStyle1="4" edges="!-444 -1103|-360 -1180" />
                    <Edge strokeStyle="1" fillStyle1="4" edges="!-360 -1180[-310 -1222 -251 -1256" />
                    <Edge strokeStyle="1" fillStyle1="4" edges="!-251 -1256|-236 -1278" />
                    <Edge strokeStyle="1" fillStyle1="4" edges="!-236 -1278|-231 -1284" />
                    <Edge strokeStyle="1" fillStyle1="4" edges="!-231 -1284[-170 -1361 -147 -1364" />
                    <Edge strokeStyle="1" fillStyle1="4" edges="!-147 -1364|-142 -1379" />
                    <Edge strokeStyle="1" edges="!-142 -1379|-142 -1383" />
                    <Edge strokeStyle="1" fillStyle0="3" fillStyle1="4" edges="!136 -1162[180 -1258 168 -1366" />
                    <Edge strokeStyle="1" fillStyle0="3" fillStyle1="4" edges="!168 -1366|166 -1381" />
                    <Edge strokeStyle="1" fillStyle0="3" fillStyle1="4" edges="!166 -1381|163 -1418" />
                    <Edge strokeStyle="1" fillStyle0="3" fillStyle1="1" edges="!163 -1418|163 -1410" />
                    <Edge strokeStyle="1" fillStyle0="1" fillStyle1="4" edges="!163 -1418|161 -1437" />
                    <Edge strokeStyle="1" fillStyle0="3" fillStyle1="4" edges="!-41 0|-42 -23" />
                    <Edge strokeStyle="1" fillStyle0="3" fillStyle1="4" edges="!-42 -23|-42 -25" />
                    <Edge strokeStyle="1" fillStyle0="3" fillStyle1="4" edges="!-42 -25|-42 -28" />
                    <Edge strokeStyle="1" fillStyle0="3" fillStyle1="4" edges="!-42 -28|-42 -30" />
                    <Edge strokeStyle="1" fillStyle0="3" fillStyle1="4" edges="!-42 -30|-42 -99" />
                    <Edge strokeStyle="1" fillStyle0="3" fillStyle1="4" edges="!-42 -99|-41 -160" />
                    <Edge strokeStyle="1" fillStyle0="3" fillStyle1="4" edges="!-41 -160|-34 -308" />
                    <Edge strokeStyle="1" fillStyle0="3" fillStyle1="4" edges="!-34 -308|-33 -312" />
                    <Edge strokeStyle="1" fillStyle0="3" fillStyle1="4" edges="!-33 -312[-18 -462 5 -607" />
                    <Edge strokeStyle="1" fillStyle0="3" fillStyle1="4" edges="!5 -607[42 -840 106 -1064" />
                    <Edge strokeStyle="1" fillStyle0="3" fillStyle1="4" edges="!106 -1064|136 -1162" />
                    <Edge strokeStyle="1" fillStyle0="3" fillStyle1="3" edges="!136 -1162|3 -1083" />
                    <Edge strokeStyle="1" fillStyle0="3" fillStyle1="3" edges="!3 -1083|-22 -1165" />
                    <Edge strokeStyle="1" fillStyle0="3" fillStyle1="2" edges="!-22 -1165|-76 -1100" />
                    <Edge strokeStyle="1" fillStyle0="3" fillStyle1="2" edges="!-76 -1100|-80 -1064" />
                    <Edge strokeStyle="1" fillStyle0="3" fillStyle1="2" edges="!-80 -1064|-89 -957" />
                    <Edge strokeStyle="1" fillStyle0="3" fillStyle1="2" edges="!-89 -957[-103 -769 -102 -569" />
                    <Edge strokeStyle="1" fillStyle0="3" fillStyle1="2" edges="!-102 -569|-106 -253" />
                    <Edge strokeStyle="1" fillStyle0="3" fillStyle1="2" edges="!-106 -253|-106 -246" />
                    <Edge strokeStyle="1" fillStyle0="3" fillStyle1="2" edges="!-106 -246|-109 -142" />
                    <Edge strokeStyle="1" fillStyle0="3" fillStyle1="2" edges="!-109 -142|-110 -124" />
                    <Edge strokeStyle="1" fillStyle0="3" fillStyle1="2" edges="!-110 -124|-172 -38" />
                    <Edge strokeStyle="1" fillStyle0="3" fillStyle1="2" edges="!-172 -38|-190 -19" />
                    <Edge strokeStyle="1" fillStyle0="4" fillStyle1="4" edges="!248 -1291|270 -993" />
                    <Edge strokeStyle="1" fillStyle0="4" fillStyle1="4" edges="!270 -993|150 -926" />
                    <Edge strokeStyle="1" fillStyle0="4" fillStyle1="4" edges="!150 -926|212 -892" />
                    <Edge strokeStyle="1" fillStyle0="4" fillStyle1="4" edges="!212 -892|249 -866" />
                    <Edge strokeStyle="1" fillStyle0="4" fillStyle1="4" edges="!249 -866|186 -748" />
                    <Edge strokeStyle="1" fillStyle0="4" fillStyle1="4" edges="!186 -748|178 -729" />
                    <Edge strokeStyle="1" fillStyle0="4" fillStyle1="4" edges="!178 -729|178 -728" />
                    <Edge strokeStyle="1" fillStyle0="4" fillStyle1="4" edges="!178 -728[128 -631 92 -546" />
                    <Edge strokeStyle="1" fillStyle0="4" fillStyle1="4" edges="!92 -546|78 -514" />
                    <Edge strokeStyle="1" fillStyle0="4" fillStyle1="4" edges="!78 -514[30 -399 2 -308" />
                    <Edge strokeStyle="1" fillStyle0="4" fillStyle1="4" edges="!2 -308|-41 -160" />
                    <Edge strokeStyle="1" fillStyle0="4" fillStyle1="4" edges="!271 199|269 199" />
                    <Edge strokeStyle="1" fillStyle0="4" fillStyle1="4" edges="!269 199|266 198" />
                    <Edge strokeStyle="1" fillStyle0="4" fillStyle1="4" edges="!266 198|265 198" />
                    <Edge strokeStyle="1" fillStyle0="4" fillStyle1="4" edges="!265 198|261 198" />
                    <Edge strokeStyle="1" fillStyle0="4" fillStyle1="4" edges="!261 198|263 -47" />
                    <Edge strokeStyle="1" fillStyle0="4" fillStyle1="4" edges="!263 -47|274 -553" />
                    <Edge strokeStyle="1" fillStyle0="4" fillStyle1="4" edges="!274 -553|274 -577" />
                    <Edge strokeStyle="1" fillStyle0="4" fillStyle1="4" edges="!274 -577|273 -601" />
                    <Edge strokeStyle="1" fillStyle0="4" fillStyle1="4" edges="!273 -601|272 -628" />
                    <Edge strokeStyle="1" fillStyle0="4" fillStyle1="4" edges="!272 -628|271 -705" />
                    <Edge strokeStyle="1" fillStyle1="4" edges="!623 172|621 196" />
                    <Edge strokeStyle="1" fillStyle1="4" edges="!621 196|621 201" />
                    <Edge strokeStyle="1" fillStyle0="4" fillStyle1="3" edges="!271 199|289 201" />
                    <Edge strokeStyle="1" fillStyle0="4" fillStyle1="3" edges="!289 201|322 207" />
                    <Edge strokeStyle="1" fillStyle0="4" fillStyle1="3" edges="!322 207|494 219" />
                    <Edge strokeStyle="1" fillStyle0="4" fillStyle1="3" edges="!494 219|501 219" />
                    <Edge strokeStyle="1" fillStyle0="4" fillStyle1="3" edges="!501 219|563 216" />
                    <Edge strokeStyle="1" fillStyle0="4" fillStyle1="3" edges="!563 216|568 216" />
                    <Edge strokeStyle="1" fillStyle0="4" fillStyle1="3" edges="!568 216|581 214" />
                    <Edge strokeStyle="1" fillStyle0="4" fillStyle1="3" edges="!581 214|595 212" />
                    <Edge strokeStyle="1" fillStyle0="1" fillStyle1="3" edges="!572 280|563 281" />
                    <Edge strokeStyle="1" fillStyle0="1" fillStyle1="3" edges="!563 281|559 281" />
                    <Edge strokeStyle="1" fillStyle0="1" fillStyle1="3" edges="!559 281|554 282" />
                    <Edge strokeStyle="1" fillStyle0="1" fillStyle1="3" edges="!554 282|501 284" />
                    <Edge strokeStyle="1" fillStyle0="1" fillStyle1="3" edges="!501 284|494 284" />
                    <Edge strokeStyle="1" fillStyle0="1" fillStyle1="3" edges="!494 284|325 272" />
                    <Edge strokeStyle="1" fillStyle0="1" fillStyle1="3" edges="!325 272|322 271" />
                    <Edge strokeStyle="1" fillStyle0="1" fillStyle1="3" edges="!322 271|289 266" />
                    <Edge strokeStyle="1" fillStyle0="1" fillStyle1="3" edges="!289 266|277 264" />
                    <Edge strokeStyle="1" fillStyle0="1" fillStyle1="3" edges="!277 264|274 264" />
                    <Edge strokeStyle="1" fillStyle0="1" fillStyle1="4" edges="!274 264|258 355" />
                    <Edge strokeStyle="1" fillStyle0="4" fillStyle1="3" edges="!274 264|263 260" />
                    <Edge strokeStyle="1" fillStyle0="4" fillStyle1="3" edges="!263 260|267 228" />
                    <Edge strokeStyle="1" fillStyle0="4" fillStyle1="3" edges="!267 228|271 199" />
                    <Edge strokeStyle="1" fillStyle0="1" fillStyle1="1" edges="!321 513[332 575 358 609" />
                    <Edge strokeStyle="1" fillStyle0="1" fillStyle1="1" edges="!401 509[432 602 501 625" />
                    <Edge strokeStyle="1" fillStyle0="1" fillStyle1="1" edges="!501 625|517 629" />
                    <Edge strokeStyle="1" fillStyle0="3" fillStyle1="4" edges="!-146 -1359|-162 -1332" />
                    <Edge strokeStyle="1" fillStyle0="3" fillStyle1="4" edges="!-162 -1332|-164 -1330" />
                    <Edge strokeStyle="1" fillStyle0="3" fillStyle1="4" edges="!-164 -1330|-194 -1259" />
                    <Edge strokeStyle="1" fillStyle0="3" fillStyle1="4" edges="!-194 -1259|-219 -1176" />
                    <Edge strokeStyle="1" fillStyle0="3" fillStyle1="4" edges="!-219 -1176|-226 -1151" />
                    <Edge strokeStyle="1" fillStyle0="3" fillStyle1="3" edges="!-226 -1151|-203 -1119" />
                    <Edge strokeStyle="1" fillStyle0="3" fillStyle1="3" edges="!-203 -1119|-182 -1093" />
                    <Edge strokeStyle="1" fillStyle0="3" fillStyle1="3" edges="!-182 -1093|-166 -1119" />
                    <Edge strokeStyle="1" fillStyle0="3" fillStyle1="3" edges="!-166 -1119|-138 -1176" />
                    <Edge strokeStyle="1" fillStyle0="3" fillStyle1="3" edges="!-138 -1176|-131 -1190" />
                    <Edge strokeStyle="1" fillStyle0="3" fillStyle1="3" edges="!-131 -1190|-127 -1198" />
                    <Edge strokeStyle="1" fillStyle0="3" fillStyle1="2" edges="!-127 -1198|-127 -1199" />
                    <Edge strokeStyle="1" fillStyle0="3" fillStyle1="2" edges="!-127 -1199|-109 -1227" />
                    <Edge strokeStyle="1" fillStyle0="3" edges="!-142 -1363|-144 -1361" />
                    <Edge strokeStyle="1" fillStyle0="3" edges="!-144 -1361|-146 -1359" />
                    <Edge strokeStyle="1" fillStyle0="4" edges="!-146 -1359|-142 -1377" />
                    <Edge strokeStyle="1" fillStyle0="3" fillStyle1="4" edges="!-226 -1151|-234 -1119" />
                    <Edge strokeStyle="1" fillStyle0="3" fillStyle1="4" edges="!-234 -1119|-256 -1005" />
                    <Edge strokeStyle="1" fillStyle0="3" fillStyle1="4" edges="!-256 -1005[-302 -738 -318 -526" />
                    <Edge strokeStyle="1" fillStyle0="3" fillStyle1="4" edges="!-318 -526|-322 -466" />
                    <Edge strokeStyle="1" fillStyle0="3" fillStyle1="4" edges="!-322 -466|-322 -465" />
                    <Edge strokeStyle="1" fillStyle0="3" fillStyle1="4" edges="!-322 -465|-340 -152" />
                    <Edge strokeStyle="1" fillStyle0="3" fillStyle1="4" edges="!-340 -152|-340 -130" />
                    <Edge strokeStyle="1" fillStyle0="3" fillStyle1="4" edges="!-340 -130|-342 -45" />
                    <Edge strokeStyle="1" fillStyle0="3" fillStyle1="4" edges="!-342 -45|-342 -23" />
                    <Edge strokeStyle="1" fillStyle0="4" fillStyle1="4" edges="!-340 -152[-342 -282 -364 -469" />
                    <Edge strokeStyle="1" fillStyle0="4" fillStyle1="4" edges="!-364 -469|-394 -707" />
                    <Edge strokeStyle="1" fillStyle0="4" fillStyle1="4" edges="!-394 -707|-418 -907" />
                    <Edge strokeStyle="1" fillStyle0="4" fillStyle1="4" edges="!-418 -907[-416 -921 -397 -924" />
                    <Edge strokeStyle="1" fillStyle0="4" fillStyle1="4" edges="!-397 -924|-337 -944" />
                    <Edge strokeStyle="1" fillStyle0="4" fillStyle1="4" edges="!-337 -944|-393 -1033" />
                    <Edge strokeStyle="1" fillStyle0="4" fillStyle1="4" edges="!-393 -1033|-331 -1144" />
                    <Edge strokeStyle="1" fillStyle0="4" fillStyle1="4" edges="!-331 -1144|-251 -1256" />
                    <Edge strokeStyle="1" fillStyle0="2" fillStyle1="3" edges="!-22 -1165[-35 -1217 -54 -1224" />
                    <Edge strokeStyle="1" fillStyle0="2" fillStyle1="3" edges="!-119 -1093|-127 -1067" />
                    <Edge strokeStyle="1" fillStyle0="2" fillStyle1="3" edges="!-127 -1067[-180 -884 -234 -566" />
                    <Edge strokeStyle="1" fillStyle0="2" fillStyle1="3" edges="!-234 -566|-295 -131" />
                    <Edge strokeStyle="1" fillStyle0="2" fillStyle1="3" edges="!-295 -131|-282 -105" />
                    <Edge strokeStyle="1" fillStyle0="2" fillStyle1="3" edges="!-282 -105|-280 -104" />
                    <Edge strokeStyle="1" fillStyle0="2" fillStyle1="3" edges="!-280 -104|-247 -30" />
                    <Edge strokeStyle="1" fillStyle0="2" fillStyle1="3" edges="!-247 -30|-246 -28" />
                    <Edge strokeStyle="1" fillStyle0="2" fillStyle1="3" edges="!-246 -28|-243 -23" />
                    <Edge strokeStyle="1" fillStyle0="2" fillStyle1="2" edges="!-119 -1093|-115 -1100" />
                    <Edge strokeStyle="1" fillStyle0="2" fillStyle1="2" edges="!-115 -1100|-76 -1100" />
                    <Edge strokeStyle="1" fillStyle0="2" fillStyle1="3" edges="!-127 -1198|-119 -1093" />
                    <Edge strokeStyle="1" fillStyle0="4" fillStyle1="4" edges="!-437 -701|-454 -569" />
                    <Edge strokeStyle="1" fillStyle0="4" fillStyle1="4" edges="!-454 -569|-460 -521" />
                    <Edge strokeStyle="1" fillStyle0="4" fillStyle1="4" edges="!-460 -521|-473 -385" />
                    <Edge strokeStyle="1" fillStyle0="4" fillStyle1="4" edges="!-473 -385|-476 -349" />
                    <Edge strokeStyle="1" fillStyle0="4" fillStyle1="4" edges="!-476 -349[-497 -104 -498 91" />
                    <Edge strokeStyle="1" fillStyle0="4" fillStyle1="4" edges="!-498 91|-498 105" />
                    <Edge strokeStyle="1" fillStyle0="4" fillStyle1="4" edges="!-498 105|-497 166" />
                    <Edge strokeStyle="1" fillStyle0="4" fillStyle1="4" edges="!-497 166|-496 190" />
                    <Edge strokeStyle="1" fillStyle0="4" fillStyle1="3" edges="!-496 190|-496 243" />
                    <Edge strokeStyle="1" fillStyle0="4" fillStyle1="3" edges="!-496 243|-496 248" />
                    <Edge strokeStyle="1" fillStyle0="4" fillStyle1="1" edges="!-496 248|-494 315" />
                    <Edge strokeStyle="1" fillStyle0="4" fillStyle1="1" edges="!-494 315|-494 316" />
                    <Edge strokeStyle="1" fillStyle0="1" fillStyle1="1" edges="!-494 316|-520 360" />
                    <Edge strokeStyle="1" fillStyle0="1" fillStyle1="1" edges="!-520 360|-519 364" />
                    <Edge strokeStyle="1" fillStyle0="1" fillStyle1="1" edges="!-519 364|-509 391" />
                    <Edge strokeStyle="1" fillStyle0="1" fillStyle1="1" edges="!-509 391[-498 419 -498 442" />
                    <Edge strokeStyle="1" fillStyle0="1" fillStyle1="1" edges="!-498 442[-498 467 -507 479" />
                    <Edge strokeStyle="1" fillStyle0="1" fillStyle1="1" edges="!-507 479[-479 504 -479 525" />
                    <Edge strokeStyle="1" fillStyle0="1" fillStyle1="1" edges="!-479 525|-479 529" />
                    <Edge strokeStyle="1" fillStyle0="3" fillStyle1="4" edges="!-496 190|-519 186" />
                    <Edge strokeStyle="1" fillStyle0="3" fillStyle1="4" edges="!-519 186|-521 186" />
                    <Edge strokeStyle="1" fillStyle0="3" fillStyle1="4" edges="!-521 186|-534 186" />
                    <Edge strokeStyle="1" fillStyle0="3" fillStyle1="4" edges="!-534 186|-582 183" />
                    <Edge strokeStyle="1" fillStyle0="3" fillStyle1="4" edges="!-582 183|-588 183" />
                    <Edge strokeStyle="1" fillStyle0="3" fillStyle1="4" edges="!-588 183|-635 179" />
                    <Edge strokeStyle="1" fillStyle0="3" fillStyle1="4" edges="!-635 179|-641 178" />
                    <Edge strokeStyle="1" fillStyle0="3" fillStyle1="4" edges="!-641 178|-649 177" />
                    <Edge strokeStyle="1" fillStyle0="3" fillStyle1="4" edges="!-649 177|-657 177" />
                    <Edge strokeStyle="1" fillStyle0="3" fillStyle1="4" edges="!-657 177|-658 177" />
                    <Edge strokeStyle="1" fillStyle0="1" fillStyle1="3" edges="!-496 248|-521 248" />
                    <Edge strokeStyle="1" fillStyle0="1" fillStyle1="3" edges="!-521 248|-612 243" />
                    <Edge strokeStyle="1" fillStyle0="1" fillStyle1="3" edges="!-612 243|-636 240" />
                    <Edge strokeStyle="1" fillStyle0="1" fillStyle1="3" edges="!-636 240|-641 238" />
                    <Edge strokeStyle="1" fillStyle0="1" fillStyle1="3" edges="!-641 238|-649 237" />
                    <Edge strokeStyle="1" fillStyle0="1" fillStyle1="3" edges="!-649 237|-657 236" />
                    <Edge strokeStyle="1" fillStyle0="1" fillStyle1="1" edges="!-617 276|-619 323" />
                    <Edge strokeStyle="1" fillStyle0="1" fillStyle1="1" edges="!-619 323[-619 366 -610 400" />
                    <Edge strokeStyle="1" fillStyle0="1" fillStyle1="1" edges="!-610 400|-584 457" />
                    <Edge strokeStyle="1" fillStyle0="1" fillStyle1="1" edges="!-584 457[-558 493 -536 493" />
                    <Edge strokeStyle="1" fillStyle0="1" fillStyle1="1" edges="!-536 493[-516 493 -507 479" />
                  </edges>
                </DOMShape>
              </elements>
            </DOMFrame>
          </frames>
        </DOMLayer>
      </layers>
    </DOMTimeline>
  </timeline>
</DOMSymbolItem>
